pyhclrs-0.0.1.dist-info/METADATA
pyhclrs-0.0.1.dist-info/WHEEL
pyhclrs-0.0.1.dist-info/license_files/LICENSE-APACHE
pyhclrs-0.0.1.dist-info/license_files/LICENSE-MIT
pyhclrs/__init__.py
pyhclrs/pyhclrs.cpython-311-darwin.so
pyhclrs-0.0.1.dist-info/RECORD
