Metadata-Version: 2.1
Name: pyhclrs
Version: 0.0.1
Classifier: Programming Language :: Rust
Classifier: Programming Language :: Python :: Implementation :: CPython
Classifier: Programming Language :: Python :: Implementation :: PyPy
License-File: LICENSE-APACHE
License-File: LICENSE-MIT
Requires-Python: >=3.7
